[
  {
    "stockCode": "SBUX",
    "stockName": "Starbucks",
    "currentPrice": 100.41000366210938,
    "periodStart": "31/10/2024",
    "periodEnd": "29/01/2025",
    "attractivePriceUberLow": 77,
    "attractivePriceStart": 83,
    "percentageProgressToAttractivePriceStart": -20.975908026637796,
    "url": "https://www.trading212.com/pl/trading-instruments/invest/SBUX.US",
    "type": "Stock"
  },
  {
    "stockCode": "IUSQ.DE",
    "stockName": "IShares MSCI ACWI (Acc)",
    "currentPrice": 87.51000213623047,
    "periodStart": "31/10/2024",
    "periodEnd": "29/01/2025",
    "attractivePriceUberLow": 80,
    "attractivePriceStart": 84.5,
    "percentageProgressToAttractivePriceStart": -3.562132705598202,
    "url": "https://www.trading212.com/pl/trading-instruments/invest/IUSQ.DE",
    "type": "Stock"
  },
  {
    "stockCode": "MCD",
    "stockName": "McDonalds",
    "currentPrice": 291.1499938964844,
    "periodStart": "31/10/2024",
    "periodEnd": "29/01/2025",
    "attractivePriceUberLow": 233,
    "attractivePriceStart": 252.8,
    "percentageProgressToAttractivePriceStart": -15.170092522343495,
    "url": "https://www.trading212.com/pl/trading-instruments/invest/MCD.US",
    "type": "Stock"
  },
  {
    "stockCode": "O",
    "stockName": "Realty Income",
    "currentPrice": 54.97999954223633,
    "periodStart": "31/10/2024",
    "periodEnd": "29/01/2025",
    "attractivePriceUberLow": 43,
    "attractivePriceStart": 59.2,
    "percentageProgressToAttractivePriceStart": 7.128379151627826,
    "url": "https://www.trading212.com/pl/trading-instruments/invest/O.US",
    "type": "Stock"
  },
  {
    "stockCode": "JNJ",
    "stockName": "Johnson & Johnson",
    "currentPrice": 150.3800048828125,
    "periodStart": "31/10/2024",
    "periodEnd": "29/01/2025",
    "attractivePriceUberLow": 145.5,
    "attractivePriceStart": 150,
    "percentageProgressToAttractivePriceStart": -0.2533365885416714,
    "url": "https://www.trading212.com/pl/trading-instruments/invest/JNJ.US",
    "type": "Stock"
  },
  {
    "stockCode": "KO",
    "stockName": "Coca-Cola",
    "currentPrice": 62.36000061035156,
    "periodStart": "31/10/2024",
    "periodEnd": "29/01/2025",
    "attractivePriceUberLow": 53,
    "attractivePriceStart": 56.8,
    "percentageProgressToAttractivePriceStart": -9.788733468928811,
    "url": "https://www.trading212.com/pl/trading-instruments/invest/KO.US",
    "type": "Stock"
  },
  {
    "stockCode": "CSCO",
    "stockName": "Cisco",
    "currentPrice": 59.43000030517578,
    "periodStart": "31/10/2024",
    "periodEnd": "29/01/2025",
    "attractivePriceUberLow": 40,
    "attractivePriceStart": 44,
    "percentageProgressToAttractivePriceStart": -35.068182511763126,
    "url": "https://www.trading212.com/pl/trading-instruments/invest/CSCO.US",
    "type": "Stock"
  },
  {
    "stockCode": "BP.L",
    "stockName": "BP",
    "currentPrice": 418.3500061035156,
    "periodStart": "31/10/2024",
    "periodEnd": "29/01/2025",
    "attractivePriceUberLow": 430,
    "attractivePriceStart": 448,
    "percentageProgressToAttractivePriceStart": 6.618302209036685,
    "url": "https://www.trading212.com/pl/trading-instruments/invest/BP.GB",
    "type": "Stock"
  },
  {
    "stockCode": "PPG",
    "stockName": "PPG",
    "currentPrice": 123.01000213623047,
    "periodStart": "31/10/2024",
    "periodEnd": "29/01/2025",
    "attractivePriceUberLow": 111,
    "attractivePriceStart": 120,
    "percentageProgressToAttractivePriceStart": -2.5083351135253906,
    "url": "https://www.trading212.com/pl/trading-instruments/invest/PPG.US",
    "type": "Stock"
  },
  {
    "stockCode": "stellar",
    "stockName": "Stellar",
    "currentPrice": 1.6007751822331113,
    "periodStart": "31/10/2024",
    "periodEnd": "29/01/2025",
    "attractivePriceStart": 0.496,
    "attractivePriceUberLow": 0.32,
    "percentageProgressToAttractivePriceStart": -222.73693190183695,
    "url": "https://www.coingecko.com/pl/waluty/stellar",
    "type": "Coin"
  },
  {
    "stockCode": "polygon-ecosystem-token",
    "stockName": "POL (ex-MATIC) (POL)",
    "currentPrice": 1.6009325867727944,
    "periodStart": "31/10/2024",
    "periodEnd": "29/01/2025",
    "attractivePriceStart": 1.6,
    "attractivePriceUberLow": 1.21,
    "percentageProgressToAttractivePriceStart": -0.05828667329963366,
    "url": "https://www.coingecko.com/pl/waluty/pol-ex-matic",
    "type": "Coin"
  },
  {
    "stockCode": "eos",
    "stockName": "EOS (EOS)",
    "currentPrice": 2.9761846703685206,
    "periodStart": "31/10/2024",
    "periodEnd": "29/01/2025",
    "attractivePriceStart": 2.4,
    "attractivePriceUberLow": 2,
    "percentageProgressToAttractivePriceStart": -24.007694598688374,
    "url": "https://www.coingecko.com/pl/waluty/eos",
    "type": "Coin"
  },
  {
    "stockCode": "stepn",
    "stockName": "GMT",
    "currentPrice": 0.36703630228771833,
    "periodStart": "31/10/2024",
    "periodEnd": "29/01/2025",
    "attractivePriceStart": 0.6,
    "attractivePriceUberLow": 0.37,
    "percentageProgressToAttractivePriceStart": 38.827282952046936,
    "url": "https://www.coingecko.com/pl/waluty/stepn",
    "type": "Coin"
  },
  {
    "stockCode": "book-of-meme",
    "stockName": "BOOK OF MEME (BOME)",
    "currentPrice": 0.012613242071271905,
    "periodStart": "31/10/2024",
    "periodEnd": "29/01/2025",
    "attractivePriceStart": 0.024,
    "attractivePriceUberLow": 0.02,
    "percentageProgressToAttractivePriceStart": 47.44482470303373,
    "url": "https://www.coingecko.com/pl/waluty/book-of-meme",
    "type": "Coin"
  },
  {
    "stockCode": "litecoin",
    "stockName": "Litecoin",
    "currentPrice": 456.1740646287437,
    "periodStart": "31/10/2024",
    "periodEnd": "29/01/2025",
    "attractivePriceStart": 320,
    "attractivePriceUberLow": 200,
    "percentageProgressToAttractivePriceStart": -42.5543951964824,
    "url": "https://www.coingecko.com/pl/waluty/litecoin",
    "type": "Coin"
  },
  {
    "stockCode": "shiba-inu",
    "stockName": "Shiba Inu",
    "currentPrice": 0.00007384518148773407,
    "periodStart": "31/10/2024",
    "periodEnd": "29/01/2025",
    "attractivePriceStart": 0.00006,
    "attractivePriceUberLow": 0.00005,
    "percentageProgressToAttractivePriceStart": -23.075302479556782,
    "url": "https://www.coingecko.com/pl/waluty/shiba-inu",
    "type": "Coin"
  },
  {
    "stockCode": "bio-protocol",
    "stockName": "Bio Protocol",
    "currentPrice": 0.901961486500886,
    "periodStart": "31/10/2024",
    "periodEnd": "29/01/2025",
    "attractivePriceStart": 1.6,
    "attractivePriceUberLow": 1.5,
    "percentageProgressToAttractivePriceStart": 43.62740709369463,
    "url": "https://www.coingecko.com/pl/waluty/bio-protocol",
    "type": "Coin"
  },
  {
    "stockCode": "avalanche-2",
    "stockName": "Avalanche",
    "currentPrice": 131.64214628047785,
    "periodStart": "31/10/2024",
    "periodEnd": "29/01/2025",
    "attractivePriceStart": 80,
    "attractivePriceUberLow": 39,
    "percentageProgressToAttractivePriceStart": -64.55268285059731,
    "url": "https://www.coingecko.com/pl/waluty/avalanche",
    "type": "Coin"
  },
  {
    "stockCode": "aave",
    "stockName": "Aave",
    "currentPrice": 1170.5665666260893,
    "periodStart": "31/10/2024",
    "periodEnd": "29/01/2025",
    "attractivePriceStart": 312,
    "attractivePriceUberLow": 222,
    "percentageProgressToAttractivePriceStart": -275.18159186733635,
    "url": "https://www.coingecko.com/pl/waluty/aave",
    "type": "Coin"
  },
  {
    "stockCode": "hedera-hashgraph",
    "stockName": "Hedera",
    "currentPrice": 1.2201361017875816,
    "periodStart": "31/10/2024",
    "periodEnd": "29/01/2025",
    "attractivePriceStart": 0.256,
    "attractivePriceUberLow": 0.17,
    "percentageProgressToAttractivePriceStart": -376.61566476077405,
    "url": "https://www.coingecko.com/pl/waluty/hedera",
    "type": "Coin"
  },
  {
    "stockCode": "steem",
    "stockName": "Steem",
    "currentPrice": 0.8317227561240075,
    "periodStart": "31/10/2024",
    "periodEnd": "29/01/2025",
    "attractivePriceStart": 0.8,
    "attractivePriceUberLow": 0.72,
    "percentageProgressToAttractivePriceStart": -3.965344515500931,
    "url": "https://www.coingecko.com/pl/waluty/steem",
    "type": "Coin"
  },
  {
    "stockCode": "chainlink",
    "stockName": "Chainlink",
    "currentPrice": 93.42144367458964,
    "periodStart": "31/10/2024",
    "periodEnd": "29/01/2025",
    "attractivePriceStart": 40,
    "attractivePriceUberLow": 21,
    "percentageProgressToAttractivePriceStart": -133.5536091864741,
    "url": "https://www.coingecko.com/pl/waluty/chainlink",
    "type": "Coin"
  },
  {
    "stockCode": "ethena",
    "stockName": "Ethena",
    "currentPrice": 2.729378011226667,
    "periodStart": "31/10/2024",
    "periodEnd": "29/01/2025",
    "attractivePriceStart": 5,
    "attractivePriceUberLow": 1,
    "percentageProgressToAttractivePriceStart": 45.41243977546666,
    "url": "https://www.coingecko.com/pl/waluty/ethena",
    "type": "Coin"
  },
  {
    "stockCode": "movement",
    "stockName": "Movement",
    "currentPrice": 3.377088648170678,
    "periodStart": "31/10/2024",
    "periodEnd": "29/01/2025",
    "attractivePriceStart": 2.76,
    "attractivePriceUberLow": 2.5,
    "percentageProgressToAttractivePriceStart": -22.35828435401008,
    "url": "https://www.coingecko.com/pl/waluty/movement",
    "type": "Coin"
  },
  {
    "stockCode": "arbitrum",
    "stockName": "Arbitrum",
    "currentPrice": 2.4344759060885597,
    "periodStart": "31/10/2024",
    "periodEnd": "29/01/2025",
    "attractivePriceStart": 3.2,
    "attractivePriceUberLow": 1.9,
    "percentageProgressToAttractivePriceStart": 23.922627934732503,
    "url": "https://www.coingecko.com/pl/waluty/arbitrum",
    "type": "Coin"
  },
  {
    "stockCode": "tron",
    "stockName": "Tron",
    "currentPrice": 0.9738826948545114,
    "periodStart": "31/10/2024",
    "periodEnd": "29/01/2025",
    "attractivePriceStart": 0.4,
    "attractivePriceUberLow": 0.24,
    "percentageProgressToAttractivePriceStart": -143.47067371362786,
    "url": "https://www.coingecko.com/pl/waluty/tron",
    "type": "Coin"
  },
  {
    "stockCode": "binance-coin-wormhole",
    "stockName": "Binance coin",
    "currentPrice": 2711.466335803204,
    "periodStart": "31/10/2024",
    "periodEnd": "29/01/2025",
    "attractivePriceStart": 2501,
    "attractivePriceUberLow": 1932,
    "percentageProgressToAttractivePriceStart": -8.415287317201276,
    "url": "https://www.coingecko.com/pl/waluty/bnb",
    "type": "Coin"
  },
  {
    "stockCode": "ethereum",
    "stockName": "Ethereum",
    "currentPrice": 12579.156330749953,
    "periodStart": "31/10/2024",
    "periodEnd": "29/01/2025",
    "attractivePriceStart": 7200,
    "attractivePriceUberLow": 5736,
    "percentageProgressToAttractivePriceStart": -74.71050459374936,
    "url": "https://www.coingecko.com/pl/waluty/ethereum",
    "type": "Coin"
  },
  {
    "stockCode": "pudgy-penguins",
    "stockName": "Pudgy Penguins",
    "currentPrice": 0.06601041073379871,
    "periodStart": "31/10/2024",
    "periodEnd": "29/01/2025",
    "attractivePriceStart": 0.13,
    "attractivePriceUberLow": 0.1,
    "percentageProgressToAttractivePriceStart": 49.222760974001,
    "url": "https://www.coingecko.com/pl/waluty/pudgy-penguins",
    "type": "Coin"
  },
  {
    "stockCode": "doge",
    "stockName": "Doge",
    "currentPrice": 0.002585560775389458,
    "periodStart": "31/10/2024",
    "periodEnd": "29/01/2025",
    "attractivePriceStart": 1.55,
    "attractivePriceUberLow": 1.3,
    "percentageProgressToAttractivePriceStart": 99.83318962739423,
    "url": "https://www.coingecko.com/pl/waluty/dogecoin",
    "type": "Coin"
  },
  {
    "stockCode": "solana",
    "stockName": "Solana",
    "currentPrice": 928.6990943786053,
    "periodStart": "31/10/2024",
    "periodEnd": "29/01/2025",
    "attractivePriceStart": 616,
    "attractivePriceUberLow": 558,
    "percentageProgressToAttractivePriceStart": -50.76283999652685,
    "url": "https://www.coingecko.com/pl/waluty/solana",
    "type": "Coin"
  },
  {
    "stockCode": "pepe",
    "stockName": "Pepe",
    "currentPrice": 0.000048931219096251575,
    "periodStart": "31/10/2024",
    "periodEnd": "29/01/2025",
    "attractivePriceStart": 0.0000368,
    "attractivePriceUberLow": 0.000042,
    "percentageProgressToAttractivePriceStart": -32.96526928329234,
    "url": "https://www.coingecko.com/pl/waluty/pepe",
    "type": "Coin"
  },
  {
    "stockCode": "cardano",
    "stockName": "Cardano",
    "currentPrice": 3.770460295821385,
    "periodStart": "31/10/2024",
    "periodEnd": "29/01/2025",
    "attractivePriceStart": 2.32,
    "attractivePriceUberLow": 1.25,
    "percentageProgressToAttractivePriceStart": -62.51984033712867,
    "url": "",
    "type": "Coin"
  },
  {
    "stockCode": "dymension",
    "stockName": "Dymension",
    "currentPrice": 3.5842639945687362,
    "periodStart": "31/10/2024",
    "periodEnd": "29/01/2025",
    "attractivePriceStart": 8,
    "attractivePriceUberLow": 5,
    "percentageProgressToAttractivePriceStart": 55.196700067890795,
    "url": "https://www.coingecko.com/pl/waluty/dymension",
    "type": "Coin"
  },
  {
    "stockCode": "render-token",
    "stockName": "Render token",
    "currentPrice": 23.13011624200639,
    "periodStart": "31/10/2024",
    "periodEnd": "29/01/2025",
    "attractivePriceStart": 24,
    "attractivePriceUberLow": 6,
    "percentageProgressToAttractivePriceStart": 3.6245156583067057,
    "url": "https://www.coingecko.com/pl/waluty/render",
    "type": "Coin"
  },
  {
    "stockCode": "usual",
    "stockName": "Usual",
    "currentPrice": 1.1844052461835846,
    "periodStart": "31/10/2024",
    "periodEnd": "29/01/2025",
    "attractivePriceStart": 2.4,
    "attractivePriceUberLow": 2,
    "percentageProgressToAttractivePriceStart": 50.64978140901731,
    "url": "https://www.coingecko.com/pl/waluty/usual",
    "type": "Coin"
  },
  {
    "stockCode": "thorchain",
    "stockName": "THORChain",
    "currentPrice": 8.432560810351513,
    "periodStart": "31/10/2024",
    "periodEnd": "29/01/2025",
    "attractivePriceStart": 20,
    "attractivePriceUberLow": 3.5,
    "percentageProgressToAttractivePriceStart": 57.83719594824244,
    "url": "https://www.coingecko.com/pl/waluty/thorchain",
    "type": "Coin"
  },
  {
    "stockCode": "bitcoin-cash",
    "stockName": "Bitcoin cash",
    "currentPrice": 1665.785187218648,
    "periodStart": "31/10/2024",
    "periodEnd": "29/01/2025",
    "attractivePriceStart": 1492,
    "attractivePriceUberLow": 446,
    "percentageProgressToAttractivePriceStart": -11.647800751920116,
    "url": "https://www.coingecko.com/pl/waluty/bitcoin-cash",
    "type": "Coin"
  },
  {
    "stockCode": "adventure-gold",
    "stockName": "Adventure gold",
    "currentPrice": 5.723630449515026,
    "periodStart": "31/10/2024",
    "periodEnd": "29/01/2025",
    "attractivePriceStart": 5.36,
    "attractivePriceUberLow": 1.23,
    "percentageProgressToAttractivePriceStart": -6.7841501775191375,
    "url": "https://www.coingecko.com/pl/waluty/adventure-gold",
    "type": "Coin"
  },
  {
    "stockCode": "dogwifcoin",
    "stockName": "Dogwifcoin",
    "currentPrice": 5.051225378716992,
    "periodStart": "31/10/2024",
    "periodEnd": "29/01/2025",
    "attractivePriceStart": 8,
    "attractivePriceUberLow": 5,
    "percentageProgressToAttractivePriceStart": 36.85968276603761,
    "url": "https://www.coingecko.com/pl/waluty/dogwifhat",
    "type": "Coin"
  }
]