[
  {
    "stockCode": "SBUX",
    "stockName": "Starbucks",
    "currentPrice": 101.125,
    "periodStart": "11/12/2024",
    "periodEnd": "11/03/2025",
    "attractivePriceUberLow": 77,
    "attractivePriceStart": 83,
    "percentageProgressToAttractivePriceStart": -21.837349397590373,
    "url": "https://www.trading212.com/pl/trading-instruments/invest/SBUX.US",
    "type": "Stock"
  },
  {
    "stockCode": "IUSQ.DE",
    "stockName": "IShares MSCI ACWI (Acc)",
    "currentPrice": 81.4800033569336,
    "periodStart": "11/12/2024",
    "periodEnd": "11/03/2025",
    "attractivePriceUberLow": 80,
    "attractivePriceStart": 84.5,
    "percentageProgressToAttractivePriceStart": 3.5739605243389434,
    "url": "https://www.trading212.com/pl/trading-instruments/invest/IUSQ.DE",
    "type": "Stock"
  },
  {
    "stockCode": "MCD",
    "stockName": "McDonalds",
    "currentPrice": 317.25,
    "periodStart": "11/12/2024",
    "periodEnd": "11/03/2025",
    "attractivePriceUberLow": 233,
    "attractivePriceStart": 252.8,
    "percentageProgressToAttractivePriceStart": -25.494462025316437,
    "url": "https://www.trading212.com/pl/trading-instruments/invest/MCD.US",
    "type": "Stock"
  },
  {
    "stockCode": "O",
    "stockName": "Realty Income",
    "currentPrice": 58.4900016784668,
    "periodStart": "11/12/2024",
    "periodEnd": "11/03/2025",
    "attractivePriceUberLow": 43,
    "attractivePriceStart": 59.2,
    "percentageProgressToAttractivePriceStart": 1.1993214890763682,
    "url": "https://www.trading212.com/pl/trading-instruments/invest/O.US",
    "type": "Stock"
  },
  {
    "stockCode": "JNJ",
    "stockName": "Johnson & Johnson",
    "currentPrice": 167.6999969482422,
    "periodStart": "11/12/2024",
    "periodEnd": "11/03/2025",
    "attractivePriceUberLow": 145.5,
    "attractivePriceStart": 150,
    "percentageProgressToAttractivePriceStart": -11.799997965494796,
    "url": "https://www.trading212.com/pl/trading-instruments/invest/JNJ.US",
    "type": "Stock"
  },
  {
    "stockCode": "KO",
    "stockName": "Coca-Cola",
    "currentPrice": 71.44999694824219,
    "periodStart": "11/12/2024",
    "periodEnd": "11/03/2025",
    "attractivePriceUberLow": 53,
    "attractivePriceStart": 56.8,
    "percentageProgressToAttractivePriceStart": -25.792248148313718,
    "url": "https://www.trading212.com/pl/trading-instruments/invest/KO.US",
    "type": "Stock"
  },
  {
    "stockCode": "CSCO",
    "stockName": "Cisco",
    "currentPrice": 62.060001373291016,
    "periodStart": "11/12/2024",
    "periodEnd": "11/03/2025",
    "attractivePriceUberLow": 40,
    "attractivePriceStart": 44,
    "percentageProgressToAttractivePriceStart": -41.045457666570485,
    "url": "https://www.trading212.com/pl/trading-instruments/invest/CSCO.US",
    "type": "Stock"
  },
  {
    "stockCode": "BP.L",
    "stockName": "BP",
    "currentPrice": 418.45001220703125,
    "periodStart": "11/12/2024",
    "periodEnd": "11/03/2025",
    "attractivePriceUberLow": 430,
    "attractivePriceStart": 448,
    "percentageProgressToAttractivePriceStart": 6.595979418073384,
    "url": "https://www.trading212.com/pl/trading-instruments/invest/BP.GB",
    "type": "Stock"
  },
  {
    "stockCode": "PPG",
    "stockName": "PPG",
    "currentPrice": 114.69000244140625,
    "periodStart": "11/12/2024",
    "periodEnd": "11/03/2025",
    "attractivePriceUberLow": 111,
    "attractivePriceStart": 120,
    "percentageProgressToAttractivePriceStart": 4.424997965494796,
    "url": "https://www.trading212.com/pl/trading-instruments/invest/PPG.US",
    "type": "Stock"
  },
  {
    "stockCode": "stellar",
    "stockName": "Stellar",
    "currentPrice": 0.9531275597399852,
    "periodStart": "11/12/2024",
    "periodEnd": "11/03/2025",
    "attractivePriceStart": 0.496,
    "attractivePriceUberLow": 0.32,
    "percentageProgressToAttractivePriceStart": -92.1628144637067,
    "url": "https://www.coingecko.com/pl/waluty/stellar",
    "type": "Coin"
  },
  {
    "stockCode": "polygon-ecosystem-token",
    "stockName": "POL (ex-MATIC) (POL)",
    "currentPrice": 0.8018253455939182,
    "periodStart": "11/12/2024",
    "periodEnd": "11/03/2025",
    "attractivePriceStart": 1.6,
    "attractivePriceUberLow": 1.21,
    "percentageProgressToAttractivePriceStart": 49.88591590038012,
    "url": "https://www.coingecko.com/pl/waluty/pol-ex-matic",
    "type": "Coin"
  },
  {
    "stockCode": "eos",
    "stockName": "EOS (EOS)",
    "currentPrice": 1.7917273161520506,
    "periodStart": "11/12/2024",
    "periodEnd": "11/03/2025",
    "attractivePriceStart": 2.4,
    "attractivePriceUberLow": 2,
    "percentageProgressToAttractivePriceStart": 25.344695160331227,
    "url": "https://www.coingecko.com/pl/waluty/eos",
    "type": "Coin"
  },
  {
    "stockCode": "stepn",
    "stockName": "GMT",
    "currentPrice": 0.17421008309243652,
    "periodStart": "11/12/2024",
    "periodEnd": "11/03/2025",
    "attractivePriceStart": 0.6,
    "attractivePriceUberLow": 0.37,
    "percentageProgressToAttractivePriceStart": 70.96498615126058,
    "url": "https://www.coingecko.com/pl/waluty/stepn",
    "type": "Coin"
  },
  {
    "stockCode": "book-of-meme",
    "stockName": "BOOK OF MEME (BOME)",
    "currentPrice": 0.00492553724330801,
    "periodStart": "11/12/2024",
    "periodEnd": "11/03/2025",
    "attractivePriceStart": 0.024,
    "attractivePriceUberLow": 0.02,
    "percentageProgressToAttractivePriceStart": 79.47692815288329,
    "url": "https://www.coingecko.com/pl/waluty/book-of-meme",
    "type": "Coin"
  },
  {
    "stockCode": "litecoin",
    "stockName": "Litecoin",
    "currentPrice": 339.91655127537695,
    "periodStart": "11/12/2024",
    "periodEnd": "11/03/2025",
    "attractivePriceStart": 320,
    "attractivePriceUberLow": 200,
    "percentageProgressToAttractivePriceStart": -6.223922273555303,
    "url": "https://www.coingecko.com/pl/waluty/litecoin",
    "type": "Coin"
  },
  {
    "stockCode": "shiba-inu",
    "stockName": "Shiba Inu",
    "currentPrice": 0.00004493316254153033,
    "periodStart": "11/12/2024",
    "periodEnd": "11/03/2025",
    "attractivePriceStart": 0.00006,
    "attractivePriceUberLow": 0.00005,
    "percentageProgressToAttractivePriceStart": 25.11139576411611,
    "url": "https://www.coingecko.com/pl/waluty/shiba-inu",
    "type": "Coin"
  },
  {
    "stockCode": "bio-protocol",
    "stockName": "Bio Protocol",
    "currentPrice": 0.32260019133306583,
    "periodStart": "11/12/2024",
    "periodEnd": "11/03/2025",
    "attractivePriceStart": 1.6,
    "attractivePriceUberLow": 1.5,
    "percentageProgressToAttractivePriceStart": 79.83748804168339,
    "url": "https://www.coingecko.com/pl/waluty/bio-protocol",
    "type": "Coin"
  },
  {
    "stockCode": "avalanche-2",
    "stockName": "Avalanche",
    "currentPrice": 63.878400921811966,
    "periodStart": "11/12/2024",
    "periodEnd": "11/03/2025",
    "attractivePriceStart": 80,
    "attractivePriceUberLow": 39,
    "percentageProgressToAttractivePriceStart": 20.151998847735044,
    "url": "https://www.coingecko.com/pl/waluty/avalanche",
    "type": "Coin"
  },
  {
    "stockCode": "aave",
    "stockName": "Aave",
    "currentPrice": 700.5273650065176,
    "periodStart": "11/12/2024",
    "periodEnd": "11/03/2025",
    "attractivePriceStart": 312,
    "attractivePriceUberLow": 222,
    "percentageProgressToAttractivePriceStart": -124.5280016046531,
    "url": "https://www.coingecko.com/pl/waluty/aave",
    "type": "Coin"
  },
  {
    "stockCode": "hedera-hashgraph",
    "stockName": "Hedera",
    "currentPrice": 0.7395752832210651,
    "periodStart": "11/12/2024",
    "periodEnd": "11/03/2025",
    "attractivePriceStart": 0.256,
    "attractivePriceUberLow": 0.17,
    "percentageProgressToAttractivePriceStart": -188.89659500822853,
    "url": "https://www.coingecko.com/pl/waluty/hedera",
    "type": "Coin"
  },
  {
    "stockCode": "steem",
    "stockName": "Steem",
    "currentPrice": 0.47207351194227437,
    "periodStart": "11/12/2024",
    "periodEnd": "11/03/2025",
    "attractivePriceStart": 0.8,
    "attractivePriceUberLow": 0.72,
    "percentageProgressToAttractivePriceStart": 40.99081100721571,
    "url": "https://www.coingecko.com/pl/waluty/steem",
    "type": "Coin"
  },
  {
    "stockCode": "chainlink",
    "stockName": "Chainlink",
    "currentPrice": 49.50121604384098,
    "periodStart": "11/12/2024",
    "periodEnd": "11/03/2025",
    "attractivePriceStart": 40,
    "attractivePriceUberLow": 21,
    "percentageProgressToAttractivePriceStart": -23.753040109602438,
    "url": "https://www.coingecko.com/pl/waluty/chainlink",
    "type": "Coin"
  },
  {
    "stockCode": "ethena",
    "stockName": "Ethena",
    "currentPrice": 1.6238805226780673,
    "periodStart": "11/12/2024",
    "periodEnd": "11/03/2025",
    "attractivePriceStart": 5,
    "attractivePriceUberLow": 1,
    "percentageProgressToAttractivePriceStart": 67.52238954643866,
    "url": "https://www.coingecko.com/pl/waluty/ethena",
    "type": "Coin"
  },
  {
    "stockCode": "movement",
    "stockName": "Movement",
    "currentPrice": 1.973640877758101,
    "periodStart": "11/12/2024",
    "periodEnd": "11/03/2025",
    "attractivePriceStart": 2.76,
    "attractivePriceUberLow": 2.5,
    "percentageProgressToAttractivePriceStart": 28.491272544996335,
    "url": "https://www.coingecko.com/pl/waluty/movement",
    "type": "Coin"
  },
  {
    "stockCode": "arbitrum",
    "stockName": "Arbitrum",
    "currentPrice": 1.25338242700947,
    "periodStart": "11/12/2024",
    "periodEnd": "11/03/2025",
    "attractivePriceStart": 3.2,
    "attractivePriceUberLow": 1.9,
    "percentageProgressToAttractivePriceStart": 60.831799155954066,
    "url": "https://www.coingecko.com/pl/waluty/arbitrum",
    "type": "Coin"
  },
  {
    "stockCode": "tron",
    "stockName": "Tron",
    "currentPrice": 0.8922920217816056,
    "periodStart": "11/12/2024",
    "periodEnd": "11/03/2025",
    "attractivePriceStart": 0.4,
    "attractivePriceUberLow": 0.24,
    "percentageProgressToAttractivePriceStart": -123.0730054454014,
    "url": "https://www.coingecko.com/pl/waluty/tron",
    "type": "Coin"
  },
  {
    "stockCode": "binance-coin-wormhole",
    "stockName": "Binance coin",
    "currentPrice": 2075.5971701480244,
    "periodStart": "11/12/2024",
    "periodEnd": "11/03/2025",
    "attractivePriceStart": 2501,
    "attractivePriceUberLow": 1932,
    "percentageProgressToAttractivePriceStart": 17.009309470290916,
    "url": "https://www.coingecko.com/pl/waluty/bnb",
    "type": "Coin"
  },
  {
    "stockCode": "ethereum",
    "stockName": "Ethereum",
    "currentPrice": 7294.026347087898,
    "periodStart": "11/12/2024",
    "periodEnd": "11/03/2025",
    "attractivePriceStart": 7200,
    "attractivePriceUberLow": 5736,
    "percentageProgressToAttractivePriceStart": -1.3059214873319291,
    "url": "https://www.coingecko.com/pl/waluty/ethereum",
    "type": "Coin"
  },
  {
    "stockCode": "pudgy-penguins",
    "stockName": "Pudgy Penguins",
    "currentPrice": 0.021855557990659476,
    "periodStart": "11/12/2024",
    "periodEnd": "11/03/2025",
    "attractivePriceStart": 0.13,
    "attractivePriceUberLow": 0.1,
    "percentageProgressToAttractivePriceStart": 83.18803231487733,
    "url": "https://www.coingecko.com/pl/waluty/pudgy-penguins",
    "type": "Coin"
  },
  {
    "stockCode": "doge",
    "stockName": "Doge",
    "currentPrice": 0.0007666425837679344,
    "periodStart": "11/12/2024",
    "periodEnd": "11/03/2025",
    "attractivePriceStart": 1.55,
    "attractivePriceUberLow": 1.3,
    "percentageProgressToAttractivePriceStart": 99.950539188144,
    "url": "https://www.coingecko.com/pl/waluty/dogecoin",
    "type": "Coin"
  },
  {
    "stockCode": "solana",
    "stockName": "Solana",
    "currentPrice": 461.9221793899422,
    "periodStart": "11/12/2024",
    "periodEnd": "11/03/2025",
    "attractivePriceStart": 616,
    "attractivePriceUberLow": 558,
    "percentageProgressToAttractivePriceStart": 25.012633215918484,
    "url": "https://www.coingecko.com/pl/waluty/solana",
    "type": "Coin"
  },
  {
    "stockCode": "pepe",
    "stockName": "Pepe",
    "currentPrice": 0.000022324293296590308,
    "periodStart": "11/12/2024",
    "periodEnd": "11/03/2025",
    "attractivePriceStart": 0.0000368,
    "attractivePriceUberLow": 0.000042,
    "percentageProgressToAttractivePriceStart": 39.33615952013504,
    "url": "https://www.coingecko.com/pl/waluty/pepe",
    "type": "Coin"
  },
  {
    "stockCode": "cardano",
    "stockName": "Cardano",
    "currentPrice": 2.6464339636626018,
    "periodStart": "11/12/2024",
    "periodEnd": "11/03/2025",
    "attractivePriceStart": 2.32,
    "attractivePriceUberLow": 1.25,
    "percentageProgressToAttractivePriceStart": -14.070429468215593,
    "url": "",
    "type": "Coin"
  },
  {
    "stockCode": "dymension",
    "stockName": "Dymension",
    "currentPrice": 1.1899342087035372,
    "periodStart": "11/12/2024",
    "periodEnd": "11/03/2025",
    "attractivePriceStart": 8,
    "attractivePriceUberLow": 5,
    "percentageProgressToAttractivePriceStart": 85.12582239120579,
    "url": "https://www.coingecko.com/pl/waluty/dymension",
    "type": "Coin"
  },
  {
    "stockCode": "render-token",
    "stockName": "Render token",
    "currentPrice": 10.754977744733925,
    "periodStart": "11/12/2024",
    "periodEnd": "11/03/2025",
    "attractivePriceStart": 24,
    "attractivePriceUberLow": 6,
    "percentageProgressToAttractivePriceStart": 55.18759273027531,
    "url": "https://www.coingecko.com/pl/waluty/render",
    "type": "Coin"
  },
  {
    "stockCode": "usual",
    "stockName": "Usual",
    "currentPrice": 0.6488640231834328,
    "periodStart": "11/12/2024",
    "periodEnd": "11/03/2025",
    "attractivePriceStart": 2.4,
    "attractivePriceUberLow": 2,
    "percentageProgressToAttractivePriceStart": 72.96399903402363,
    "url": "https://www.coingecko.com/pl/waluty/usual",
    "type": "Coin"
  },
  {
    "stockCode": "thorchain",
    "stockName": "THORChain",
    "currentPrice": 4.001205433758039,
    "periodStart": "11/12/2024",
    "periodEnd": "11/03/2025",
    "attractivePriceStart": 20,
    "attractivePriceUberLow": 3.5,
    "percentageProgressToAttractivePriceStart": 79.9939728312098,
    "url": "https://www.coingecko.com/pl/waluty/thorchain",
    "type": "Coin"
  },
  {
    "stockCode": "bitcoin-cash",
    "stockName": "Bitcoin cash",
    "currentPrice": 1302.8803036316015,
    "periodStart": "11/12/2024",
    "periodEnd": "11/03/2025",
    "attractivePriceStart": 1492,
    "attractivePriceUberLow": 446,
    "percentageProgressToAttractivePriceStart": 12.675582866514645,
    "url": "https://www.coingecko.com/pl/waluty/bitcoin-cash",
    "type": "Coin"
  },
  {
    "stockCode": "adventure-gold",
    "stockName": "Adventure gold",
    "currentPrice": 3.8832685581114657,
    "periodStart": "11/12/2024",
    "periodEnd": "11/03/2025",
    "attractivePriceStart": 5.36,
    "attractivePriceUberLow": 1.23,
    "percentageProgressToAttractivePriceStart": 27.550959736726384,
    "url": "https://www.coingecko.com/pl/waluty/adventure-gold",
    "type": "Coin"
  },
  {
    "stockCode": "dogwifcoin",
    "stockName": "Dogwifcoin",
    "currentPrice": 1.678159352595337,
    "periodStart": "11/12/2024",
    "periodEnd": "11/03/2025",
    "attractivePriceStart": 8,
    "attractivePriceUberLow": 5,
    "percentageProgressToAttractivePriceStart": 79.02300809255829,
    "url": "https://www.coingecko.com/pl/waluty/dogwifhat",
    "type": "Coin"
  }
]