[
  {
    "stockCode": "SBUX",
    "stockName": "Starbucks",
    "currentPrice": 106.4800033569336,
    "periodStart": "10/12/2024",
    "periodEnd": "10/03/2025",
    "attractivePriceUberLow": 77,
    "attractivePriceStart": 83,
    "percentageProgressToAttractivePriceStart": -28.28916067100434,
    "url": "https://www.trading212.com/pl/trading-instruments/invest/SBUX.US",
    "type": "Stock"
  },
  {
    "stockCode": "IUSQ.DE",
    "stockName": "IShares MSCI ACWI (Acc)",
    "currentPrice": 82.12000274658203,
    "periodStart": "10/12/2024",
    "periodEnd": "10/03/2025",
    "attractivePriceUberLow": 80,
    "attractivePriceStart": 84.5,
    "percentageProgressToAttractivePriceStart": 2.8165647969443484,
    "url": "https://www.trading212.com/pl/trading-instruments/invest/IUSQ.DE",
    "type": "Stock"
  },
  {
    "stockCode": "MCD",
    "stockName": "McDonalds",
    "currentPrice": 321.2900085449219,
    "periodStart": "10/12/2024",
    "periodEnd": "10/03/2025",
    "attractivePriceUberLow": 233,
    "attractivePriceStart": 252.8,
    "percentageProgressToAttractivePriceStart": -27.092566671250722,
    "url": "https://www.trading212.com/pl/trading-instruments/invest/MCD.US",
    "type": "Stock"
  },
  {
    "stockCode": "O",
    "stockName": "Realty Income",
    "currentPrice": 58.47999954223633,
    "periodStart": "10/12/2024",
    "periodEnd": "10/03/2025",
    "attractivePriceUberLow": 43,
    "attractivePriceStart": 59.2,
    "percentageProgressToAttractivePriceStart": 1.2162169894656643,
    "url": "https://www.trading212.com/pl/trading-instruments/invest/O.US",
    "type": "Stock"
  },
  {
    "stockCode": "JNJ",
    "stockName": "Johnson & Johnson",
    "currentPrice": 166.69000244140625,
    "periodStart": "10/12/2024",
    "periodEnd": "10/03/2025",
    "attractivePriceUberLow": 145.5,
    "attractivePriceStart": 150,
    "percentageProgressToAttractivePriceStart": -11.126668294270829,
    "url": "https://www.trading212.com/pl/trading-instruments/invest/JNJ.US",
    "type": "Stock"
  },
  {
    "stockCode": "KO",
    "stockName": "Coca-Cola",
    "currentPrice": 71.43000030517578,
    "periodStart": "10/12/2024",
    "periodEnd": "10/03/2025",
    "attractivePriceUberLow": 53,
    "attractivePriceStart": 56.8,
    "percentageProgressToAttractivePriceStart": -25.757042790802444,
    "url": "https://www.trading212.com/pl/trading-instruments/invest/KO.US",
    "type": "Stock"
  },
  {
    "stockCode": "CSCO",
    "stockName": "Cisco",
    "currentPrice": 63.939998626708984,
    "periodStart": "10/12/2024",
    "periodEnd": "10/03/2025",
    "attractivePriceUberLow": 40,
    "attractivePriceStart": 44,
    "percentageProgressToAttractivePriceStart": -45.31817869706586,
    "url": "https://www.trading212.com/pl/trading-instruments/invest/CSCO.US",
    "type": "Stock"
  },
  {
    "stockCode": "BP.L",
    "stockName": "BP",
    "currentPrice": 413.45001220703125,
    "periodStart": "10/12/2024",
    "periodEnd": "10/03/2025",
    "attractivePriceUberLow": 430,
    "attractivePriceStart": 448,
    "percentageProgressToAttractivePriceStart": 7.712050846644814,
    "url": "https://www.trading212.com/pl/trading-instruments/invest/BP.GB",
    "type": "Stock"
  },
  {
    "stockCode": "PPG",
    "stockName": "PPG",
    "currentPrice": 115.4800033569336,
    "periodStart": "10/12/2024",
    "periodEnd": "10/03/2025",
    "attractivePriceUberLow": 111,
    "attractivePriceStart": 120,
    "percentageProgressToAttractivePriceStart": 3.7666638692220147,
    "url": "https://www.trading212.com/pl/trading-instruments/invest/PPG.US",
    "type": "Stock"
  },
  {
    "stockCode": "stellar",
    "stockName": "Stellar",
    "currentPrice": 1.0306676195127176,
    "periodStart": "10/12/2024",
    "periodEnd": "10/03/2025",
    "attractivePriceStart": 0.496,
    "attractivePriceUberLow": 0.32,
    "percentageProgressToAttractivePriceStart": -107.79589103078982,
    "url": "https://www.coingecko.com/pl/waluty/stellar",
    "type": "Coin"
  },
  {
    "stockCode": "polygon-ecosystem-token",
    "stockName": "POL (ex-MATIC) (POL)",
    "currentPrice": 0.8713219646144066,
    "periodStart": "10/12/2024",
    "periodEnd": "10/03/2025",
    "attractivePriceStart": 1.6,
    "attractivePriceUberLow": 1.21,
    "percentageProgressToAttractivePriceStart": 45.54237721159959,
    "url": "https://www.coingecko.com/pl/waluty/pol-ex-matic",
    "type": "Coin"
  },
  {
    "stockCode": "eos",
    "stockName": "EOS (EOS)",
    "currentPrice": 1.9217189232434881,
    "periodStart": "10/12/2024",
    "periodEnd": "10/03/2025",
    "attractivePriceStart": 2.4,
    "attractivePriceUberLow": 2,
    "percentageProgressToAttractivePriceStart": 19.928378198187986,
    "url": "https://www.coingecko.com/pl/waluty/eos",
    "type": "Coin"
  },
  {
    "stockCode": "stepn",
    "stockName": "GMT",
    "currentPrice": 0.1799115599689927,
    "periodStart": "10/12/2024",
    "periodEnd": "10/03/2025",
    "attractivePriceStart": 0.6,
    "attractivePriceUberLow": 0.37,
    "percentageProgressToAttractivePriceStart": 70.01474000516788,
    "url": "https://www.coingecko.com/pl/waluty/stepn",
    "type": "Coin"
  },
  {
    "stockCode": "book-of-meme",
    "stockName": "BOOK OF MEME (BOME)",
    "currentPrice": 0.005134180645461716,
    "periodStart": "10/12/2024",
    "periodEnd": "10/03/2025",
    "attractivePriceStart": 0.024,
    "attractivePriceUberLow": 0.02,
    "percentageProgressToAttractivePriceStart": 78.60758064390951,
    "url": "https://www.coingecko.com/pl/waluty/book-of-meme",
    "type": "Coin"
  },
  {
    "stockCode": "litecoin",
    "stockName": "Litecoin",
    "currentPrice": 372.8596403380322,
    "periodStart": "10/12/2024",
    "periodEnd": "10/03/2025",
    "attractivePriceStart": 320,
    "attractivePriceUberLow": 200,
    "percentageProgressToAttractivePriceStart": -16.51863760563505,
    "url": "https://www.coingecko.com/pl/waluty/litecoin",
    "type": "Coin"
  },
  {
    "stockCode": "shiba-inu",
    "stockName": "Shiba Inu",
    "currentPrice": 0.00004726828744356879,
    "periodStart": "10/12/2024",
    "periodEnd": "10/03/2025",
    "attractivePriceStart": 0.00006,
    "attractivePriceUberLow": 0.00005,
    "percentageProgressToAttractivePriceStart": 21.219520927385346,
    "url": "https://www.coingecko.com/pl/waluty/shiba-inu",
    "type": "Coin"
  },
  {
    "stockCode": "bio-protocol",
    "stockName": "Bio Protocol",
    "currentPrice": 0.3291332870901919,
    "periodStart": "10/12/2024",
    "periodEnd": "10/03/2025",
    "attractivePriceStart": 1.6,
    "attractivePriceUberLow": 1.5,
    "percentageProgressToAttractivePriceStart": 79.429169556863,
    "url": "https://www.coingecko.com/pl/waluty/bio-protocol",
    "type": "Coin"
  },
  {
    "stockCode": "avalanche-2",
    "stockName": "Avalanche",
    "currentPrice": 70.90609692367283,
    "periodStart": "10/12/2024",
    "periodEnd": "10/03/2025",
    "attractivePriceStart": 80,
    "attractivePriceUberLow": 39,
    "percentageProgressToAttractivePriceStart": 11.367378845408965,
    "url": "https://www.coingecko.com/pl/waluty/avalanche",
    "type": "Coin"
  },
  {
    "stockCode": "aave",
    "stockName": "Aave",
    "currentPrice": 748.4582502391512,
    "periodStart": "10/12/2024",
    "periodEnd": "10/03/2025",
    "attractivePriceStart": 312,
    "attractivePriceUberLow": 222,
    "percentageProgressToAttractivePriceStart": -139.89046482024077,
    "url": "https://www.coingecko.com/pl/waluty/aave",
    "type": "Coin"
  },
  {
    "stockCode": "hedera-hashgraph",
    "stockName": "Hedera",
    "currentPrice": 0.8081914049925684,
    "periodStart": "10/12/2024",
    "periodEnd": "10/03/2025",
    "attractivePriceStart": 0.256,
    "attractivePriceUberLow": 0.17,
    "percentageProgressToAttractivePriceStart": -215.69976757522198,
    "url": "https://www.coingecko.com/pl/waluty/hedera",
    "type": "Coin"
  },
  {
    "stockCode": "steem",
    "stockName": "Steem",
    "currentPrice": 0.49425139103444626,
    "periodStart": "10/12/2024",
    "periodEnd": "10/03/2025",
    "attractivePriceStart": 0.8,
    "attractivePriceUberLow": 0.72,
    "percentageProgressToAttractivePriceStart": 38.21857612069422,
    "url": "https://www.coingecko.com/pl/waluty/steem",
    "type": "Coin"
  },
  {
    "stockCode": "chainlink",
    "stockName": "Chainlink",
    "currentPrice": 55.00138597652715,
    "periodStart": "10/12/2024",
    "periodEnd": "10/03/2025",
    "attractivePriceStart": 40,
    "attractivePriceUberLow": 21,
    "percentageProgressToAttractivePriceStart": -37.5034649413179,
    "url": "https://www.coingecko.com/pl/waluty/chainlink",
    "type": "Coin"
  },
  {
    "stockCode": "ethena",
    "stockName": "Ethena",
    "currentPrice": 1.7727826294373001,
    "periodStart": "10/12/2024",
    "periodEnd": "10/03/2025",
    "attractivePriceStart": 5,
    "attractivePriceUberLow": 1,
    "percentageProgressToAttractivePriceStart": 64.544347411254,
    "url": "https://www.coingecko.com/pl/waluty/ethena",
    "type": "Coin"
  },
  {
    "stockCode": "movement",
    "stockName": "Movement",
    "currentPrice": 1.8464820165553912,
    "periodStart": "10/12/2024",
    "periodEnd": "10/03/2025",
    "attractivePriceStart": 2.76,
    "attractivePriceUberLow": 2.5,
    "percentageProgressToAttractivePriceStart": 33.09847766103654,
    "url": "https://www.coingecko.com/pl/waluty/movement",
    "type": "Coin"
  },
  {
    "stockCode": "arbitrum",
    "stockName": "Arbitrum",
    "currentPrice": 1.3806021466467158,
    "periodStart": "10/12/2024",
    "periodEnd": "10/03/2025",
    "attractivePriceStart": 3.2,
    "attractivePriceUberLow": 1.9,
    "percentageProgressToAttractivePriceStart": 56.856182917290134,
    "url": "https://www.coingecko.com/pl/waluty/arbitrum",
    "type": "Coin"
  },
  {
    "stockCode": "tron",
    "stockName": "Tron",
    "currentPrice": 0.9060507773320616,
    "periodStart": "10/12/2024",
    "periodEnd": "10/03/2025",
    "attractivePriceStart": 0.4,
    "attractivePriceUberLow": 0.24,
    "percentageProgressToAttractivePriceStart": -126.51269433301539,
    "url": "https://www.coingecko.com/pl/waluty/tron",
    "type": "Coin"
  },
  {
    "stockCode": "binance-coin-wormhole",
    "stockName": "Binance coin",
    "currentPrice": 2172.4500201128026,
    "periodStart": "10/12/2024",
    "periodEnd": "10/03/2025",
    "attractivePriceStart": 2501,
    "attractivePriceUberLow": 1932,
    "percentageProgressToAttractivePriceStart": 13.136744497688824,
    "url": "https://www.coingecko.com/pl/waluty/bnb",
    "type": "Coin"
  },
  {
    "stockCode": "ethereum",
    "stockName": "Ethereum",
    "currentPrice": 7995.711598129477,
    "periodStart": "10/12/2024",
    "periodEnd": "10/03/2025",
    "attractivePriceStart": 7200,
    "attractivePriceUberLow": 5736,
    "percentageProgressToAttractivePriceStart": -11.051549974020517,
    "url": "https://www.coingecko.com/pl/waluty/ethereum",
    "type": "Coin"
  },
  {
    "stockCode": "pudgy-penguins",
    "stockName": "Pudgy Penguins",
    "currentPrice": 0.021958504374224194,
    "periodStart": "10/12/2024",
    "periodEnd": "10/03/2025",
    "attractivePriceStart": 0.13,
    "attractivePriceUberLow": 0.1,
    "percentageProgressToAttractivePriceStart": 83.10884278905831,
    "url": "https://www.coingecko.com/pl/waluty/pudgy-penguins",
    "type": "Coin"
  },
  {
    "stockCode": "doge",
    "stockName": "Doge",
    "currentPrice": 0.0008473249771284378,
    "periodStart": "10/12/2024",
    "periodEnd": "10/03/2025",
    "attractivePriceStart": 1.55,
    "attractivePriceUberLow": 1.3,
    "percentageProgressToAttractivePriceStart": 99.94533387244333,
    "url": "https://www.coingecko.com/pl/waluty/dogecoin",
    "type": "Coin"
  },
  {
    "stockCode": "solana",
    "stockName": "Solana",
    "currentPrice": 494.94645864724623,
    "periodStart": "10/12/2024",
    "periodEnd": "10/03/2025",
    "attractivePriceStart": 616,
    "attractivePriceUberLow": 558,
    "percentageProgressToAttractivePriceStart": 19.65154892090159,
    "url": "https://www.coingecko.com/pl/waluty/solana",
    "type": "Coin"
  },
  {
    "stockCode": "pepe",
    "stockName": "Pepe",
    "currentPrice": 0.00002349809959403322,
    "periodStart": "10/12/2024",
    "periodEnd": "10/03/2025",
    "attractivePriceStart": 0.0000368,
    "attractivePriceUberLow": 0.000042,
    "percentageProgressToAttractivePriceStart": 36.146468494474945,
    "url": "https://www.coingecko.com/pl/waluty/pepe",
    "type": "Coin"
  },
  {
    "stockCode": "cardano",
    "stockName": "Cardano",
    "currentPrice": 2.875848024717847,
    "periodStart": "10/12/2024",
    "periodEnd": "10/03/2025",
    "attractivePriceStart": 2.32,
    "attractivePriceUberLow": 1.25,
    "percentageProgressToAttractivePriceStart": -23.958966582665823,
    "url": "",
    "type": "Coin"
  },
  {
    "stockCode": "dymension",
    "stockName": "Dymension",
    "currentPrice": 1.2085661699824315,
    "periodStart": "10/12/2024",
    "periodEnd": "10/03/2025",
    "attractivePriceStart": 8,
    "attractivePriceUberLow": 5,
    "percentageProgressToAttractivePriceStart": 84.89292287521961,
    "url": "https://www.coingecko.com/pl/waluty/dymension",
    "type": "Coin"
  },
  {
    "stockCode": "render-token",
    "stockName": "Render token",
    "currentPrice": 11.941219348957686,
    "periodStart": "10/12/2024",
    "periodEnd": "10/03/2025",
    "attractivePriceStart": 24,
    "attractivePriceUberLow": 6,
    "percentageProgressToAttractivePriceStart": 50.244919379342974,
    "url": "https://www.coingecko.com/pl/waluty/render",
    "type": "Coin"
  },
  {
    "stockCode": "usual",
    "stockName": "Usual",
    "currentPrice": 0.6692991674209186,
    "periodStart": "10/12/2024",
    "periodEnd": "10/03/2025",
    "attractivePriceStart": 2.4,
    "attractivePriceUberLow": 2,
    "percentageProgressToAttractivePriceStart": 72.11253469079506,
    "url": "https://www.coingecko.com/pl/waluty/usual",
    "type": "Coin"
  },
  {
    "stockCode": "thorchain",
    "stockName": "THORChain",
    "currentPrice": 4.89367753519326,
    "periodStart": "10/12/2024",
    "periodEnd": "10/03/2025",
    "attractivePriceStart": 20,
    "attractivePriceUberLow": 3.5,
    "percentageProgressToAttractivePriceStart": 75.5316123240337,
    "url": "https://www.coingecko.com/pl/waluty/thorchain",
    "type": "Coin"
  },
  {
    "stockCode": "bitcoin-cash",
    "stockName": "Bitcoin cash",
    "currentPrice": 1393.9062857528613,
    "periodStart": "10/12/2024",
    "periodEnd": "10/03/2025",
    "attractivePriceStart": 1492,
    "attractivePriceUberLow": 446,
    "percentageProgressToAttractivePriceStart": 6.574645727020027,
    "url": "https://www.coingecko.com/pl/waluty/bitcoin-cash",
    "type": "Coin"
  },
  {
    "stockCode": "adventure-gold",
    "stockName": "Adventure gold",
    "currentPrice": 4.2465774351732355,
    "periodStart": "10/12/2024",
    "periodEnd": "10/03/2025",
    "attractivePriceStart": 5.36,
    "attractivePriceUberLow": 1.23,
    "percentageProgressToAttractivePriceStart": 20.772809045275466,
    "url": "https://www.coingecko.com/pl/waluty/adventure-gold",
    "type": "Coin"
  },
  {
    "stockCode": "dogwifcoin",
    "stockName": "Dogwifcoin",
    "currentPrice": 1.7661459105201125,
    "periodStart": "10/12/2024",
    "periodEnd": "10/03/2025",
    "attractivePriceStart": 8,
    "attractivePriceUberLow": 5,
    "percentageProgressToAttractivePriceStart": 77.92317611849859,
    "url": "https://www.coingecko.com/pl/waluty/dogwifhat",
    "type": "Coin"
  }
]