[
  {
    "stockCode": "SBUX",
    "stockName": "Starbucks",
    "currentPrice": 112.19999694824219,
    "periodStart": "11/11/2024",
    "periodEnd": "09/02/2025",
    "attractivePriceUberLow": 77,
    "attractivePriceStart": 83,
    "percentageProgressToAttractivePriceStart": -35.180719214749644,
    "url": "https://www.trading212.com/pl/trading-instruments/invest/SBUX.US",
    "type": "Stock"
  },
  {
    "stockCode": "IUSQ.DE",
    "stockName": "IShares MSCI ACWI (Acc)",
    "currentPrice": 88.91000366210938,
    "periodStart": "11/11/2024",
    "periodEnd": "09/02/2025",
    "attractivePriceUberLow": 80,
    "attractivePriceStart": 84.5,
    "percentageProgressToAttractivePriceStart": -5.218939245099861,
    "url": "https://www.trading212.com/pl/trading-instruments/invest/IUSQ.DE",
    "type": "Stock"
  },
  {
    "stockCode": "MCD",
    "stockName": "McDonalds",
    "currentPrice": 294.29998779296875,
    "periodStart": "11/11/2024",
    "periodEnd": "09/02/2025",
    "attractivePriceUberLow": 233,
    "attractivePriceStart": 252.8,
    "percentageProgressToAttractivePriceStart": -16.4161344117756,
    "url": "https://www.trading212.com/pl/trading-instruments/invest/MCD.US",
    "type": "Stock"
  },
  {
    "stockCode": "O",
    "stockName": "Realty Income",
    "currentPrice": 54.119998931884766,
    "periodStart": "11/11/2024",
    "periodEnd": "09/02/2025",
    "attractivePriceUberLow": 43,
    "attractivePriceStart": 59.2,
    "percentageProgressToAttractivePriceStart": 8.581082885329792,
    "url": "https://www.trading212.com/pl/trading-instruments/invest/O.US",
    "type": "Stock"
  },
  {
    "stockCode": "JNJ",
    "stockName": "Johnson & Johnson",
    "currentPrice": 153.1199951171875,
    "periodStart": "11/11/2024",
    "periodEnd": "09/02/2025",
    "attractivePriceUberLow": 145.5,
    "attractivePriceStart": 150,
    "percentageProgressToAttractivePriceStart": -2.0799967447916714,
    "url": "https://www.trading212.com/pl/trading-instruments/invest/JNJ.US",
    "type": "Stock"
  },
  {
    "stockCode": "KO",
    "stockName": "Coca-Cola",
    "currentPrice": 63.84000015258789,
    "periodStart": "11/11/2024",
    "periodEnd": "09/02/2025",
    "attractivePriceUberLow": 53,
    "attractivePriceStart": 56.8,
    "percentageProgressToAttractivePriceStart": -12.394366465823751,
    "url": "https://www.trading212.com/pl/trading-instruments/invest/KO.US",
    "type": "Stock"
  },
  {
    "stockCode": "CSCO",
    "stockName": "Cisco",
    "currentPrice": 62.27000045776367,
    "periodStart": "11/11/2024",
    "periodEnd": "09/02/2025",
    "attractivePriceUberLow": 40,
    "attractivePriceStart": 44,
    "percentageProgressToAttractivePriceStart": -41.522728313099236,
    "url": "https://www.trading212.com/pl/trading-instruments/invest/CSCO.US",
    "type": "Stock"
  },
  {
    "stockCode": "BP.L",
    "stockName": "BP",
    "currentPrice": 433.25,
    "periodStart": "11/11/2024",
    "periodEnd": "09/02/2025",
    "attractivePriceUberLow": 430,
    "attractivePriceStart": 448,
    "percentageProgressToAttractivePriceStart": 3.292410714285708,
    "url": "https://www.trading212.com/pl/trading-instruments/invest/BP.GB",
    "type": "Stock"
  },
  {
    "stockCode": "PPG",
    "stockName": "PPG",
    "currentPrice": 114.83999633789062,
    "periodStart": "11/11/2024",
    "periodEnd": "09/02/2025",
    "attractivePriceUberLow": 111,
    "attractivePriceStart": 120,
    "percentageProgressToAttractivePriceStart": 4.3000030517578125,
    "url": "https://www.trading212.com/pl/trading-instruments/invest/PPG.US",
    "type": "Stock"
  },
  {
    "stockCode": "stellar",
    "stockName": "Stellar",
    "currentPrice": 1.366234350143935,
    "periodStart": "11/11/2024",
    "periodEnd": "09/02/2025",
    "attractivePriceStart": 0.496,
    "attractivePriceUberLow": 0.32,
    "percentageProgressToAttractivePriceStart": -175.4504738193417,
    "url": "https://www.coingecko.com/pl/waluty/stellar",
    "type": "Coin"
  },
  {
    "stockCode": "polygon-ecosystem-token",
    "stockName": "POL (ex-MATIC) (POL)",
    "currentPrice": 1.2823400106591056,
    "periodStart": "11/11/2024",
    "periodEnd": "09/02/2025",
    "attractivePriceStart": 1.6,
    "attractivePriceUberLow": 1.21,
    "percentageProgressToAttractivePriceStart": 19.853749333805908,
    "url": "https://www.coingecko.com/pl/waluty/pol-ex-matic",
    "type": "Coin"
  },
  {
    "stockCode": "eos",
    "stockName": "EOS (EOS)",
    "currentPrice": 2.505256742379839,
    "periodStart": "11/11/2024",
    "periodEnd": "09/02/2025",
    "attractivePriceStart": 2.4,
    "attractivePriceUberLow": 2,
    "percentageProgressToAttractivePriceStart": -4.385697599159968,
    "url": "https://www.coingecko.com/pl/waluty/eos",
    "type": "Coin"
  },
  {
    "stockCode": "stepn",
    "stockName": "GMT",
    "currentPrice": 0.2891814838104316,
    "periodStart": "11/11/2024",
    "periodEnd": "09/02/2025",
    "attractivePriceStart": 0.6,
    "attractivePriceUberLow": 0.37,
    "percentageProgressToAttractivePriceStart": 51.803086031594724,
    "url": "https://www.coingecko.com/pl/waluty/stepn",
    "type": "Coin"
  },
  {
    "stockCode": "book-of-meme",
    "stockName": "BOOK OF MEME (BOME)",
    "currentPrice": 0.008705799966051897,
    "periodStart": "11/11/2024",
    "periodEnd": "09/02/2025",
    "attractivePriceStart": 0.024,
    "attractivePriceUberLow": 0.02,
    "percentageProgressToAttractivePriceStart": 63.72583347478377,
    "url": "https://www.coingecko.com/pl/waluty/book-of-meme",
    "type": "Coin"
  },
  {
    "stockCode": "litecoin",
    "stockName": "Litecoin",
    "currentPrice": 436.00077874755743,
    "periodStart": "11/11/2024",
    "periodEnd": "09/02/2025",
    "attractivePriceStart": 320,
    "attractivePriceUberLow": 200,
    "percentageProgressToAttractivePriceStart": -36.2502433586117,
    "url": "https://www.coingecko.com/pl/waluty/litecoin",
    "type": "Coin"
  },
  {
    "stockCode": "shiba-inu",
    "stockName": "Shiba Inu",
    "currentPrice": 0.00006639456015766953,
    "periodStart": "11/11/2024",
    "periodEnd": "09/02/2025",
    "attractivePriceStart": 0.00006,
    "attractivePriceUberLow": 0.00005,
    "percentageProgressToAttractivePriceStart": -10.657600262782552,
    "url": "https://www.coingecko.com/pl/waluty/shiba-inu",
    "type": "Coin"
  },
  {
    "stockCode": "bio-protocol",
    "stockName": "Bio Protocol",
    "currentPrice": 0.5744064245223199,
    "periodStart": "11/11/2024",
    "periodEnd": "09/02/2025",
    "attractivePriceStart": 1.6,
    "attractivePriceUberLow": 1.5,
    "percentageProgressToAttractivePriceStart": 64.09959846735501,
    "url": "https://www.coingecko.com/pl/waluty/bio-protocol",
    "type": "Coin"
  },
  {
    "stockCode": "avalanche-2",
    "stockName": "Avalanche",
    "currentPrice": 102.24785944845162,
    "periodStart": "11/11/2024",
    "periodEnd": "09/02/2025",
    "attractivePriceStart": 80,
    "attractivePriceUberLow": 39,
    "percentageProgressToAttractivePriceStart": -27.809824310564537,
    "url": "https://www.coingecko.com/pl/waluty/avalanche",
    "type": "Coin"
  },
  {
    "stockCode": "aave",
    "stockName": "Aave",
    "currentPrice": 1019.2281096244836,
    "periodStart": "11/11/2024",
    "periodEnd": "09/02/2025",
    "attractivePriceStart": 312,
    "attractivePriceUberLow": 222,
    "percentageProgressToAttractivePriceStart": -226.6756761616935,
    "url": "https://www.coingecko.com/pl/waluty/aave",
    "type": "Coin"
  },
  {
    "stockCode": "hedera-hashgraph",
    "stockName": "Hedera",
    "currentPrice": 0.9802458839084363,
    "periodStart": "11/11/2024",
    "periodEnd": "09/02/2025",
    "attractivePriceStart": 0.256,
    "attractivePriceUberLow": 0.17,
    "percentageProgressToAttractivePriceStart": -282.9085484017329,
    "url": "https://www.coingecko.com/pl/waluty/hedera",
    "type": "Coin"
  },
  {
    "stockCode": "steem",
    "stockName": "Steem",
    "currentPrice": 0.7165943435854291,
    "periodStart": "11/11/2024",
    "periodEnd": "09/02/2025",
    "attractivePriceStart": 0.8,
    "attractivePriceUberLow": 0.72,
    "percentageProgressToAttractivePriceStart": 10.425707051821377,
    "url": "https://www.coingecko.com/pl/waluty/steem",
    "type": "Coin"
  },
  {
    "stockCode": "chainlink",
    "stockName": "Chainlink",
    "currentPrice": 76.58691167284378,
    "periodStart": "11/11/2024",
    "periodEnd": "09/02/2025",
    "attractivePriceStart": 40,
    "attractivePriceUberLow": 21,
    "percentageProgressToAttractivePriceStart": -91.46727918210945,
    "url": "https://www.coingecko.com/pl/waluty/chainlink",
    "type": "Coin"
  },
  {
    "stockCode": "ethena",
    "stockName": "Ethena",
    "currentPrice": 2.170770061328345,
    "periodStart": "11/11/2024",
    "periodEnd": "09/02/2025",
    "attractivePriceStart": 5,
    "attractivePriceUberLow": 1,
    "percentageProgressToAttractivePriceStart": 56.5845987734331,
    "url": "https://www.coingecko.com/pl/waluty/ethena",
    "type": "Coin"
  },
  {
    "stockCode": "movement",
    "stockName": "Movement",
    "currentPrice": 2.2944976207251817,
    "periodStart": "11/11/2024",
    "periodEnd": "09/02/2025",
    "attractivePriceStart": 2.76,
    "attractivePriceUberLow": 2.5,
    "percentageProgressToAttractivePriceStart": 16.86602823459485,
    "url": "https://www.coingecko.com/pl/waluty/movement",
    "type": "Coin"
  },
  {
    "stockCode": "arbitrum",
    "stockName": "Arbitrum",
    "currentPrice": 1.8804430002453951,
    "periodStart": "11/11/2024",
    "periodEnd": "09/02/2025",
    "attractivePriceStart": 3.2,
    "attractivePriceUberLow": 1.9,
    "percentageProgressToAttractivePriceStart": 41.236156242331404,
    "url": "https://www.coingecko.com/pl/waluty/arbitrum",
    "type": "Coin"
  },
  {
    "stockCode": "tron",
    "stockName": "Tron",
    "currentPrice": 0.948824211915103,
    "periodStart": "11/11/2024",
    "periodEnd": "09/02/2025",
    "attractivePriceStart": 0.4,
    "attractivePriceUberLow": 0.24,
    "percentageProgressToAttractivePriceStart": -137.20605297877574,
    "url": "https://www.coingecko.com/pl/waluty/tron",
    "type": "Coin"
  },
  {
    "stockCode": "binance-coin-wormhole",
    "stockName": "Binance coin",
    "currentPrice": 2497.5808384221755,
    "periodStart": "11/11/2024",
    "periodEnd": "09/02/2025",
    "attractivePriceStart": 2501,
    "attractivePriceUberLow": 1932,
    "percentageProgressToAttractivePriceStart": 0.13671177840161874,
    "url": "https://www.coingecko.com/pl/waluty/bnb",
    "type": "Coin"
  },
  {
    "stockCode": "ethereum",
    "stockName": "Ethereum",
    "currentPrice": 10843.896933743354,
    "periodStart": "11/11/2024",
    "periodEnd": "09/02/2025",
    "attractivePriceStart": 7200,
    "attractivePriceUberLow": 5736,
    "percentageProgressToAttractivePriceStart": -50.60967963532437,
    "url": "https://www.coingecko.com/pl/waluty/ethereum",
    "type": "Coin"
  },
  {
    "stockCode": "pudgy-penguins",
    "stockName": "Pudgy Penguins",
    "currentPrice": 0.043756674223992174,
    "periodStart": "11/11/2024",
    "periodEnd": "09/02/2025",
    "attractivePriceStart": 0.13,
    "attractivePriceUberLow": 0.1,
    "percentageProgressToAttractivePriceStart": 66.34101982769832,
    "url": "https://www.coingecko.com/pl/waluty/pudgy-penguins",
    "type": "Coin"
  },
  {
    "stockCode": "doge",
    "stockName": "Doge",
    "currentPrice": 0.0021916269092834843,
    "periodStart": "11/11/2024",
    "periodEnd": "09/02/2025",
    "attractivePriceStart": 1.55,
    "attractivePriceUberLow": 1.3,
    "percentageProgressToAttractivePriceStart": 99.85860471553009,
    "url": "https://www.coingecko.com/pl/waluty/dogecoin",
    "type": "Coin"
  },
  {
    "stockCode": "solana",
    "stockName": "Solana",
    "currentPrice": 835.9699219119956,
    "periodStart": "11/11/2024",
    "periodEnd": "09/02/2025",
    "attractivePriceStart": 616,
    "attractivePriceUberLow": 558,
    "percentageProgressToAttractivePriceStart": -35.709402907791485,
    "url": "https://www.coingecko.com/pl/waluty/solana",
    "type": "Coin"
  },
  {
    "stockCode": "pepe",
    "stockName": "Pepe",
    "currentPrice": 0.00003950326713507562,
    "periodStart": "11/11/2024",
    "periodEnd": "09/02/2025",
    "attractivePriceStart": 0.0000368,
    "attractivePriceUberLow": 0.000042,
    "percentageProgressToAttractivePriceStart": -7.345834606183743,
    "url": "https://www.coingecko.com/pl/waluty/pepe",
    "type": "Coin"
  },
  {
    "stockCode": "cardano",
    "stockName": "Cardano",
    "currentPrice": 2.8832509070827332,
    "periodStart": "11/11/2024",
    "periodEnd": "09/02/2025",
    "attractivePriceStart": 2.32,
    "attractivePriceUberLow": 1.25,
    "percentageProgressToAttractivePriceStart": -24.278056339773002,
    "url": "",
    "type": "Coin"
  },
  {
    "stockCode": "dymension",
    "stockName": "Dymension",
    "currentPrice": 2.3597732727015814,
    "periodStart": "11/11/2024",
    "periodEnd": "09/02/2025",
    "attractivePriceStart": 8,
    "attractivePriceUberLow": 5,
    "percentageProgressToAttractivePriceStart": 70.50283409123023,
    "url": "https://www.coingecko.com/pl/waluty/dymension",
    "type": "Coin"
  },
  {
    "stockCode": "render-token",
    "stockName": "Render token",
    "currentPrice": 17.73700200232257,
    "periodStart": "11/11/2024",
    "periodEnd": "09/02/2025",
    "attractivePriceStart": 24,
    "attractivePriceUberLow": 6,
    "percentageProgressToAttractivePriceStart": 26.095824990322626,
    "url": "https://www.coingecko.com/pl/waluty/render",
    "type": "Coin"
  },
  {
    "stockCode": "usual",
    "stockName": "Usual",
    "currentPrice": 1.119435505185102,
    "periodStart": "11/11/2024",
    "periodEnd": "09/02/2025",
    "attractivePriceStart": 2.4,
    "attractivePriceUberLow": 2,
    "percentageProgressToAttractivePriceStart": 53.35685395062075,
    "url": "https://www.coingecko.com/pl/waluty/usual",
    "type": "Coin"
  },
  {
    "stockCode": "thorchain",
    "stockName": "THORChain",
    "currentPrice": 5.054606634505816,
    "periodStart": "11/11/2024",
    "periodEnd": "09/02/2025",
    "attractivePriceStart": 20,
    "attractivePriceUberLow": 3.5,
    "percentageProgressToAttractivePriceStart": 74.72696682747092,
    "url": "https://www.coingecko.com/pl/waluty/thorchain",
    "type": "Coin"
  },
  {
    "stockCode": "bitcoin-cash",
    "stockName": "Bitcoin cash",
    "currentPrice": 1327.3856477067588,
    "periodStart": "11/11/2024",
    "periodEnd": "09/02/2025",
    "attractivePriceStart": 1492,
    "attractivePriceUberLow": 446,
    "percentageProgressToAttractivePriceStart": 11.033133531718576,
    "url": "https://www.coingecko.com/pl/waluty/bitcoin-cash",
    "type": "Coin"
  },
  {
    "stockCode": "adventure-gold",
    "stockName": "Adventure gold",
    "currentPrice": 5.018768514065469,
    "periodStart": "11/11/2024",
    "periodEnd": "09/02/2025",
    "attractivePriceStart": 5.36,
    "attractivePriceUberLow": 1.23,
    "percentageProgressToAttractivePriceStart": 6.366259065942742,
    "url": "https://www.coingecko.com/pl/waluty/adventure-gold",
    "type": "Coin"
  },
  {
    "stockCode": "dogwifcoin",
    "stockName": "Dogwifcoin",
    "currentPrice": 2.9504303690011686,
    "periodStart": "11/11/2024",
    "periodEnd": "09/02/2025",
    "attractivePriceStart": 8,
    "attractivePriceUberLow": 5,
    "percentageProgressToAttractivePriceStart": 63.11962038748539,
    "url": "https://www.coingecko.com/pl/waluty/dogwifhat",
    "type": "Coin"
  }
]