[
  {
    "stockCode": "SBUX",
    "stockName": "Starbucks",
    "currentPrice": 111.41999816894531,
    "periodStart": "05/12/2024",
    "periodEnd": "05/03/2025",
    "attractivePriceUberLow": 77,
    "attractivePriceStart": 83,
    "percentageProgressToAttractivePriceStart": -34.240961649331695,
    "url": "https://www.trading212.com/pl/trading-instruments/invest/SBUX.US",
    "type": "Stock"
  },
  {
    "stockCode": "IUSQ.DE",
    "stockName": "IShares MSCI ACWI (Acc)",
    "currentPrice": 83.4000015258789,
    "periodStart": "05/12/2024",
    "periodEnd": "05/03/2025",
    "attractivePriceUberLow": 80,
    "attractivePriceStart": 84.5,
    "percentageProgressToAttractivePriceStart": 1.301773342155144,
    "url": "https://www.trading212.com/pl/trading-instruments/invest/IUSQ.DE",
    "type": "Stock"
  },
  {
    "stockCode": "MCD",
    "stockName": "McDonalds",
    "currentPrice": 306.4309997558594,
    "periodStart": "05/12/2024",
    "periodEnd": "05/03/2025",
    "attractivePriceUberLow": 233,
    "attractivePriceStart": 252.8,
    "percentageProgressToAttractivePriceStart": -21.21479420722285,
    "url": "https://www.trading212.com/pl/trading-instruments/invest/MCD.US",
    "type": "Stock"
  },
  {
    "stockCode": "O",
    "stockName": "Realty Income",
    "currentPrice": 57.82400131225586,
    "periodStart": "05/12/2024",
    "periodEnd": "05/03/2025",
    "attractivePriceUberLow": 43,
    "attractivePriceStart": 59.2,
    "percentageProgressToAttractivePriceStart": 2.3243221076759113,
    "url": "https://www.trading212.com/pl/trading-instruments/invest/O.US",
    "type": "Stock"
  },
  {
    "stockCode": "JNJ",
    "stockName": "Johnson & Johnson",
    "currentPrice": 164.8300018310547,
    "periodStart": "05/12/2024",
    "periodEnd": "05/03/2025",
    "attractivePriceUberLow": 145.5,
    "attractivePriceStart": 150,
    "percentageProgressToAttractivePriceStart": -9.886667887369782,
    "url": "https://www.trading212.com/pl/trading-instruments/invest/JNJ.US",
    "type": "Stock"
  },
  {
    "stockCode": "KO",
    "stockName": "Coca-Cola",
    "currentPrice": 70.40499877929688,
    "periodStart": "05/12/2024",
    "periodEnd": "05/03/2025",
    "attractivePriceUberLow": 53,
    "attractivePriceStart": 56.8,
    "percentageProgressToAttractivePriceStart": -23.952462639607177,
    "url": "https://www.trading212.com/pl/trading-instruments/invest/KO.US",
    "type": "Stock"
  },
  {
    "stockCode": "CSCO",
    "stockName": "Cisco",
    "currentPrice": 63.67499923706055,
    "periodStart": "05/12/2024",
    "periodEnd": "05/03/2025",
    "attractivePriceUberLow": 40,
    "attractivePriceStart": 44,
    "percentageProgressToAttractivePriceStart": -44.715907356955796,
    "url": "https://www.trading212.com/pl/trading-instruments/invest/CSCO.US",
    "type": "Stock"
  },
  {
    "stockCode": "BP.L",
    "stockName": "BP",
    "currentPrice": 408.20001220703125,
    "periodStart": "05/12/2024",
    "periodEnd": "05/03/2025",
    "attractivePriceUberLow": 430,
    "attractivePriceStart": 448,
    "percentageProgressToAttractivePriceStart": 8.883925846644814,
    "url": "https://www.trading212.com/pl/trading-instruments/invest/BP.GB",
    "type": "Stock"
  },
  {
    "stockCode": "PPG",
    "stockName": "PPG",
    "currentPrice": 112.2249984741211,
    "periodStart": "05/12/2024",
    "periodEnd": "05/03/2025",
    "attractivePriceUberLow": 111,
    "attractivePriceStart": 120,
    "percentageProgressToAttractivePriceStart": 6.479167938232422,
    "url": "https://www.trading212.com/pl/trading-instruments/invest/PPG.US",
    "type": "Stock"
  },
  {
    "stockCode": "stellar",
    "stockName": "Stellar",
    "currentPrice": 1.1554612044385366,
    "periodStart": "05/12/2024",
    "periodEnd": "05/03/2025",
    "attractivePriceStart": 0.496,
    "attractivePriceUberLow": 0.32,
    "percentageProgressToAttractivePriceStart": -132.95588799164045,
    "url": "https://www.coingecko.com/pl/waluty/stellar",
    "type": "Coin"
  },
  {
    "stockCode": "polygon-ecosystem-token",
    "stockName": "POL (ex-MATIC) (POL)",
    "currentPrice": 0.9667927296316381,
    "periodStart": "05/12/2024",
    "periodEnd": "05/03/2025",
    "attractivePriceStart": 1.6,
    "attractivePriceUberLow": 1.21,
    "percentageProgressToAttractivePriceStart": 39.57545439802262,
    "url": "https://www.coingecko.com/pl/waluty/pol-ex-matic",
    "type": "Coin"
  },
  {
    "stockCode": "eos",
    "stockName": "EOS (EOS)",
    "currentPrice": 2.1114735301911276,
    "periodStart": "05/12/2024",
    "periodEnd": "05/03/2025",
    "attractivePriceStart": 2.4,
    "attractivePriceUberLow": 2,
    "percentageProgressToAttractivePriceStart": 12.021936242036347,
    "url": "https://www.coingecko.com/pl/waluty/eos",
    "type": "Coin"
  },
  {
    "stockCode": "stepn",
    "stockName": "GMT",
    "currentPrice": 0.2031014303612945,
    "periodStart": "05/12/2024",
    "periodEnd": "05/03/2025",
    "attractivePriceStart": 0.6,
    "attractivePriceUberLow": 0.37,
    "percentageProgressToAttractivePriceStart": 66.14976160645091,
    "url": "https://www.coingecko.com/pl/waluty/stepn",
    "type": "Coin"
  },
  {
    "stockCode": "book-of-meme",
    "stockName": "BOOK OF MEME (BOME)",
    "currentPrice": 0.006422509313947685,
    "periodStart": "05/12/2024",
    "periodEnd": "05/03/2025",
    "attractivePriceStart": 0.024,
    "attractivePriceUberLow": 0.02,
    "percentageProgressToAttractivePriceStart": 73.23954452521798,
    "url": "https://www.coingecko.com/pl/waluty/book-of-meme",
    "type": "Coin"
  },
  {
    "stockCode": "litecoin",
    "stockName": "Litecoin",
    "currentPrice": 398.50510586535023,
    "periodStart": "05/12/2024",
    "periodEnd": "05/03/2025",
    "attractivePriceStart": 320,
    "attractivePriceUberLow": 200,
    "percentageProgressToAttractivePriceStart": -24.53284558292195,
    "url": "https://www.coingecko.com/pl/waluty/litecoin",
    "type": "Coin"
  },
  {
    "stockCode": "shiba-inu",
    "stockName": "Shiba Inu",
    "currentPrice": 0.00005077702054687937,
    "periodStart": "05/12/2024",
    "periodEnd": "05/03/2025",
    "attractivePriceStart": 0.00006,
    "attractivePriceUberLow": 0.00005,
    "percentageProgressToAttractivePriceStart": 15.371632421867716,
    "url": "https://www.coingecko.com/pl/waluty/shiba-inu",
    "type": "Coin"
  },
  {
    "stockCode": "bio-protocol",
    "stockName": "Bio Protocol",
    "currentPrice": 0.402559014253548,
    "periodStart": "05/12/2024",
    "periodEnd": "05/03/2025",
    "attractivePriceStart": 1.6,
    "attractivePriceUberLow": 1.5,
    "percentageProgressToAttractivePriceStart": 74.84006160915325,
    "url": "https://www.coingecko.com/pl/waluty/bio-protocol",
    "type": "Coin"
  },
  {
    "stockCode": "avalanche-2",
    "stockName": "Avalanche",
    "currentPrice": 79.32684715345417,
    "periodStart": "05/12/2024",
    "periodEnd": "05/03/2025",
    "attractivePriceStart": 80,
    "attractivePriceUberLow": 39,
    "percentageProgressToAttractivePriceStart": 0.8414410581822835,
    "url": "https://www.coingecko.com/pl/waluty/avalanche",
    "type": "Coin"
  },
  {
    "stockCode": "aave",
    "stockName": "Aave",
    "currentPrice": 832.4080610063257,
    "periodStart": "05/12/2024",
    "periodEnd": "05/03/2025",
    "attractivePriceStart": 312,
    "attractivePriceUberLow": 222,
    "percentageProgressToAttractivePriceStart": -166.79745545074542,
    "url": "https://www.coingecko.com/pl/waluty/aave",
    "type": "Coin"
  },
  {
    "stockCode": "hedera-hashgraph",
    "stockName": "Hedera",
    "currentPrice": 0.9404053916308633,
    "periodStart": "05/12/2024",
    "periodEnd": "05/03/2025",
    "attractivePriceStart": 0.256,
    "attractivePriceUberLow": 0.17,
    "percentageProgressToAttractivePriceStart": -267.345856105806,
    "url": "https://www.coingecko.com/pl/waluty/hedera",
    "type": "Coin"
  },
  {
    "stockCode": "steem",
    "stockName": "Steem",
    "currentPrice": 0.5472145565788975,
    "periodStart": "05/12/2024",
    "periodEnd": "05/03/2025",
    "attractivePriceStart": 0.8,
    "attractivePriceUberLow": 0.72,
    "percentageProgressToAttractivePriceStart": 31.598180427637814,
    "url": "https://www.coingecko.com/pl/waluty/steem",
    "type": "Coin"
  },
  {
    "stockCode": "chainlink",
    "stockName": "Chainlink",
    "currentPrice": 62.25522518516442,
    "periodStart": "05/12/2024",
    "periodEnd": "05/03/2025",
    "attractivePriceStart": 40,
    "attractivePriceUberLow": 21,
    "percentageProgressToAttractivePriceStart": -55.63806296291105,
    "url": "https://www.coingecko.com/pl/waluty/chainlink",
    "type": "Coin"
  },
  {
    "stockCode": "ethena",
    "stockName": "Ethena",
    "currentPrice": 1.3877710084137016,
    "periodStart": "05/12/2024",
    "periodEnd": "05/03/2025",
    "attractivePriceStart": 5,
    "attractivePriceUberLow": 1,
    "percentageProgressToAttractivePriceStart": 72.24457983172597,
    "url": "https://www.coingecko.com/pl/waluty/ethena",
    "type": "Coin"
  },
  {
    "stockCode": "movement",
    "stockName": "Movement",
    "currentPrice": 1.5655065970754931,
    "periodStart": "05/12/2024",
    "periodEnd": "05/03/2025",
    "attractivePriceStart": 2.76,
    "attractivePriceUberLow": 2.5,
    "percentageProgressToAttractivePriceStart": 43.27874648277198,
    "url": "https://www.coingecko.com/pl/waluty/movement",
    "type": "Coin"
  },
  {
    "stockCode": "arbitrum",
    "stockName": "Arbitrum",
    "currentPrice": 1.5983289733740063,
    "periodStart": "05/12/2024",
    "periodEnd": "05/03/2025",
    "attractivePriceStart": 3.2,
    "attractivePriceUberLow": 1.9,
    "percentageProgressToAttractivePriceStart": 50.05221958206231,
    "url": "https://www.coingecko.com/pl/waluty/arbitrum",
    "type": "Coin"
  },
  {
    "stockCode": "tron",
    "stockName": "Tron",
    "currentPrice": 0.938818400343823,
    "periodStart": "05/12/2024",
    "periodEnd": "05/03/2025",
    "attractivePriceStart": 0.4,
    "attractivePriceUberLow": 0.24,
    "percentageProgressToAttractivePriceStart": -134.70460008595575,
    "url": "https://www.coingecko.com/pl/waluty/tron",
    "type": "Coin"
  },
  {
    "stockCode": "binance-coin-wormhole",
    "stockName": "Binance coin",
    "currentPrice": 2280.3053097022143,
    "periodStart": "05/12/2024",
    "periodEnd": "05/03/2025",
    "attractivePriceStart": 2501,
    "attractivePriceUberLow": 1932,
    "percentageProgressToAttractivePriceStart": 8.824257908747924,
    "url": "https://www.coingecko.com/pl/waluty/bnb",
    "type": "Coin"
  },
  {
    "stockCode": "ethereum",
    "stockName": "Ethereum",
    "currentPrice": 8428.626057310446,
    "periodStart": "05/12/2024",
    "periodEnd": "05/03/2025",
    "attractivePriceStart": 7200,
    "attractivePriceUberLow": 5736,
    "percentageProgressToAttractivePriceStart": -17.064250795978424,
    "url": "https://www.coingecko.com/pl/waluty/ethereum",
    "type": "Coin"
  },
  {
    "stockCode": "pudgy-penguins",
    "stockName": "Pudgy Penguins",
    "currentPrice": 0.025228329796309006,
    "periodStart": "05/12/2024",
    "periodEnd": "05/03/2025",
    "attractivePriceStart": 0.13,
    "attractivePriceUberLow": 0.1,
    "percentageProgressToAttractivePriceStart": 80.59359246437769,
    "url": "https://www.coingecko.com/pl/waluty/pudgy-penguins",
    "type": "Coin"
  },
  {
    "stockCode": "doge",
    "stockName": "Doge",
    "currentPrice": 0.0009314663094076394,
    "periodStart": "05/12/2024",
    "periodEnd": "05/03/2025",
    "attractivePriceStart": 1.55,
    "attractivePriceUberLow": 1.3,
    "percentageProgressToAttractivePriceStart": 99.93990539939306,
    "url": "https://www.coingecko.com/pl/waluty/dogecoin",
    "type": "Coin"
  },
  {
    "stockCode": "solana",
    "stockName": "Solana",
    "currentPrice": 550.5795575516343,
    "periodStart": "05/12/2024",
    "periodEnd": "05/03/2025",
    "attractivePriceStart": 616,
    "attractivePriceUberLow": 558,
    "percentageProgressToAttractivePriceStart": 10.620201696163264,
    "url": "https://www.coingecko.com/pl/waluty/solana",
    "type": "Coin"
  },
  {
    "stockCode": "pepe",
    "stockName": "Pepe",
    "currentPrice": 0.000026980026838036102,
    "periodStart": "05/12/2024",
    "periodEnd": "05/03/2025",
    "attractivePriceStart": 0.0000368,
    "attractivePriceUberLow": 0.000042,
    "percentageProgressToAttractivePriceStart": 26.68470967924972,
    "url": "https://www.coingecko.com/pl/waluty/pepe",
    "type": "Coin"
  },
  {
    "stockCode": "cardano",
    "stockName": "Cardano",
    "currentPrice": 3.7443974078576883,
    "periodStart": "05/12/2024",
    "periodEnd": "05/03/2025",
    "attractivePriceStart": 2.32,
    "attractivePriceUberLow": 1.25,
    "percentageProgressToAttractivePriceStart": -61.39643999386587,
    "url": "",
    "type": "Coin"
  },
  {
    "stockCode": "dymension",
    "stockName": "Dymension",
    "currentPrice": 1.3610561310723108,
    "periodStart": "05/12/2024",
    "periodEnd": "05/03/2025",
    "attractivePriceStart": 8,
    "attractivePriceUberLow": 5,
    "percentageProgressToAttractivePriceStart": 82.98679836159612,
    "url": "https://www.coingecko.com/pl/waluty/dymension",
    "type": "Coin"
  },
  {
    "stockCode": "render-token",
    "stockName": "Render token",
    "currentPrice": 14.211028987193279,
    "periodStart": "05/12/2024",
    "periodEnd": "05/03/2025",
    "attractivePriceStart": 24,
    "attractivePriceUberLow": 6,
    "percentageProgressToAttractivePriceStart": 40.78737922002801,
    "url": "https://www.coingecko.com/pl/waluty/render",
    "type": "Coin"
  },
  {
    "stockCode": "usual",
    "stockName": "Usual",
    "currentPrice": 0.776359214131271,
    "periodStart": "05/12/2024",
    "periodEnd": "05/03/2025",
    "attractivePriceStart": 2.4,
    "attractivePriceUberLow": 2,
    "percentageProgressToAttractivePriceStart": 67.65169941119704,
    "url": "https://www.coingecko.com/pl/waluty/usual",
    "type": "Coin"
  },
  {
    "stockCode": "thorchain",
    "stockName": "THORChain",
    "currentPrice": 4.631487065291688,
    "periodStart": "05/12/2024",
    "periodEnd": "05/03/2025",
    "attractivePriceStart": 20,
    "attractivePriceUberLow": 3.5,
    "percentageProgressToAttractivePriceStart": 76.84256467354156,
    "url": "https://www.coingecko.com/pl/waluty/thorchain",
    "type": "Coin"
  },
  {
    "stockCode": "bitcoin-cash",
    "stockName": "Bitcoin cash",
    "currentPrice": 1494.2769188031084,
    "periodStart": "05/12/2024",
    "periodEnd": "05/03/2025",
    "attractivePriceStart": 1492,
    "attractivePriceUberLow": 446,
    "percentageProgressToAttractivePriceStart": -0.1526084988678491,
    "url": "https://www.coingecko.com/pl/waluty/bitcoin-cash",
    "type": "Coin"
  },
  {
    "stockCode": "adventure-gold",
    "stockName": "Adventure gold",
    "currentPrice": 4.897142267816007,
    "periodStart": "05/12/2024",
    "periodEnd": "05/03/2025",
    "attractivePriceStart": 5.36,
    "attractivePriceUberLow": 1.23,
    "percentageProgressToAttractivePriceStart": 8.635405451193904,
    "url": "https://www.coingecko.com/pl/waluty/adventure-gold",
    "type": "Coin"
  },
  {
    "stockCode": "dogwifcoin",
    "stockName": "Dogwifcoin",
    "currentPrice": 2.2236947792424853,
    "periodStart": "05/12/2024",
    "periodEnd": "05/03/2025",
    "attractivePriceStart": 8,
    "attractivePriceUberLow": 5,
    "percentageProgressToAttractivePriceStart": 72.20381525946894,
    "url": "https://www.coingecko.com/pl/waluty/dogwifhat",
    "type": "Coin"
  }
]